miniz/__init__.py
miniz/__version__.py
miniz/miniz.py
miniz/utils.py
miniz/dependencies/__init__.py
miniz/dependencies/miniz-Linux-arm64.so
miniz/dependencies/miniz-Linux-x86_64.so
miniz/dependencies/miniz-Windows-arm64.dll
miniz/dependencies/miniz-Windows-x86_64.dll
miniz/dependencies/miniz-macOS-arm64.dylib
miniz/dependencies/miniz-macOS-x86_64.dylib
miniz-1.0.dist-info/LICENSE
miniz-1.0.dist-info/METADATA
miniz-1.0.dist-info/WHEEL
miniz-1.0.dist-info/top_level.txt
miniz-1.0.dist-info/RECORD
